{"nodes": [{"id": "workspacepagemotion", "label": "WorkspacePageMotion.tsx", "file_type": "code", "source_file": "apps/web/components/motion/WorkspacePageMotion.tsx", "source_location": "L1"}, {"id": "workspacepagemotion_workspacepagemotion", "label": "WorkspacePageMotion()", "file_type": "code", "source_file": "apps/web/components/motion/WorkspacePageMotion.tsx", "source_location": "L6"}], "edges": [{"source": "workspacepagemotion", "target": "react", "relation": "imports_from", "confidence": "EXTRACTED", "source_file": "apps/web/components/motion/WorkspacePageMotion.tsx", "source_location": "L3", "weight": 1.0}, {"source": "workspacepagemotion", "target": "use_prefers_motion", "relation": "imports_from", "confidence": "EXTRACTED", "source_file": "apps/web/components/motion/WorkspacePageMotion.tsx", "source_location": "L4", "weight": 1.0}, {"source": "workspacepagemotion", "target": "workspacepagemotion_workspacepagemotion", "relation": "contains", "confidence": "EXTRACTED", "source_file": "apps/web/components/motion/WorkspacePageMotion.tsx", "source_location": "L6", "weight": 1.0}]}