{"nodes": [{"id": "priority_actions", "label": "priority-actions.ts", "file_type": "code", "source_file": "apps/api/src/lib/priority-actions.ts", "source_location": "L1"}, {"id": "priority_actions_comparepriorityactions", "label": "comparePriorityActions()", "file_type": "code", "source_file": "apps/api/src/lib/priority-actions.ts", "source_location": "L49"}, {"id": "priority_actions_collectpriorityactionsfromdeals", "label": "collectPriorityActionsFromDeals()", "file_type": "code", "source_file": "apps/api/src/lib/priority-actions.ts", "source_location": "L67"}], "edges": [{"source": "priority_actions", "target": "db", "relation": "imports_from", "confidence": "EXTRACTED", "source_file": "apps/api/src/lib/priority-actions.ts", "source_location": "L1", "weight": 1.0}, {"source": "priority_actions", "target": "types", "relation": "imports_from", "confidence": "EXTRACTED", "source_file": "apps/api/src/lib/priority-actions.ts", "source_location": "L2", "weight": 1.0}, {"source": "priority_actions", "target": "priority_actions_comparepriorityactions", "relation": "contains", "confidence": "EXTRACTED", "source_file": "apps/api/src/lib/priority-actions.ts", "source_location": "L49", "weight": 1.0}, {"source": "priority_actions", "target": "priority_actions_collectpriorityactionsfromdeals", "relation": "contains", "confidence": "EXTRACTED", "source_file": "apps/api/src/lib/priority-actions.ts", "source_location": "L67", "weight": 1.0}]}